jiango/crypto.py
jiango/importlib.py
jiango/settings.py
jiango/shortcuts.py
jiango/validators.py
jiango/__init__.py
jiango/account/context_processors.py
jiango/account/helpers.py
jiango/account/middleware.py
jiango/account/models.py
jiango/account/services.py
jiango/account/settings.py
jiango/account/signals.py
jiango/account/__init__.py
jiango/admin/admin.py
jiango/admin/api.py
jiango/admin/auth.py
jiango/admin/config.py
jiango/admin/forms.py
jiango/admin/loader.py
jiango/admin/middleware.py
jiango/admin/models.py
jiango/admin/shortcuts.py
jiango/admin/ui.py
jiango/admin/__init__.py
jiango/admin/management/__init__.py
jiango/admin/management/commands/admin_createuser.py
jiango/admin/management/commands/admin_syncperms.py
jiango/admin/management/commands/__init__.py
jiango/admin/static/admin/audio/notify.wav
jiango/admin/static/admin/css/admin.css
jiango/admin/static/admin/css/AdminLTE.css
jiango/admin/static/admin/css/bootstrap.css
jiango/admin/static/admin/css/daterangepicker.css
jiango/admin/static/admin/css/font-awesome.css
jiango/admin/static/admin/css/jquery.notify.css
jiango/admin/static/admin/css/skins/skin-black-light.css
jiango/admin/static/admin/css/skins/skin-blue-light.css
jiango/admin/static/admin/fonts/fontawesome-webfont.eot
jiango/admin/static/admin/fonts/fontawesome-webfont.svg
jiango/admin/static/admin/fonts/fontawesome-webfont.ttf
jiango/admin/static/admin/fonts/fontawesome-webfont.woff
jiango/admin/static/admin/fonts/fontawesome-webfont.woff2
jiango/admin/static/admin/fonts/FontAwesome.otf
jiango/admin/static/admin/fonts/glyphicons-halflings-regular.eot
jiango/admin/static/admin/fonts/glyphicons-halflings-regular.svg
jiango/admin/static/admin/fonts/glyphicons-halflings-regular.ttf
jiango/admin/static/admin/fonts/glyphicons-halflings-regular.woff
jiango/admin/static/admin/fonts/glyphicons-halflings-regular.woff2
jiango/admin/static/admin/img/close.gif
jiango/admin/static/admin/img/error.png
jiango-1.0.0.dist-info/DESCRIPTION.rst
jiango-1.0.0.dist-info/METADATA
jiango-1.0.0.dist-info/metadata.json
jiango-1.0.0.dist-info/RECORD
jiango-1.0.0.dist-info/top_level.txt
jiango-1.0.0.dist-info/WHEEL
