Metadata-Version: 2.0
Name: jiango
Version: 1.0.0
Summary: Django Framework Toolkit.
Home-page: http://y.minecon.cn
Author: Feiye
Author-email: 316606233@qq.com
License: BSD
Platform: UNKNOWN
Requires-Dist: django (<1.5,>=1.4)
